{
  "type": "FeatureCollection", 
  "features": [
    {
      "geometry": {
        "type": "Point", 
        "coordinates": [
          121.63384125, 
          31.304860744948414
        ]
      }, 
      "type": "Feature", 
      "properties": {
        "admin1_code": "", 
        "point_size": 8, 
        "name": "Shanghai", 
        "geonameid": 1796236, 
        "font_file": "../fonts/Arial.ttf", 
        "zoom_start": 4, 
        "font_size": 18, 
        "country_code": "CN", 
        "capital": "no", 
        "asciiname": "Shanghai", 
        "justified": "left", 
        "population": 14608512
      }
    }, 
    {
      "geometry": {
        "type": "Point", 
        "coordinates": [
          73.023721249999994, 
          19.105789361964536
        ]
      }, 
      "type": "Feature", 
      "properties": {
        "admin1_code": "", 
        "point_size": 8, 
        "name": "Mumbai", 
        "geonameid": 1275339, 
        "font_file": "../fonts/Arial.ttf", 
        "zoom_start": 4, 
        "font_size": 18, 
        "country_code": "IN", 
        "capital": "no", 
        "asciiname": "Mumbai", 
        "justified": "left", 
        "population": 12691836
      }
    }, 
    {
      "geometry": {
        "type": "Point", 
        "coordinates": [
          67.257981249999958, 
          24.993257570443934
        ]
      }, 
      "type": "Feature", 
      "properties": {
        "admin1_code": "", 
        "point_size": 8, 
        "name": "Karachi", 
        "geonameid": 1174872, 
        "font_file": "../fonts/Arial.ttf", 
        "zoom_start": 4, 
        "font_size": 18, 
        "country_code": "PK", 
        "capital": "no", 
        "asciiname": "Karachi", 
        "justified": "left", 
        "population": 11624219
      }
    }, 
    {
      "geometry": {
        "type": "Point", 
        "coordinates": [
          121.14641125, 
          14.678124459133235
        ]
      }, 
      "type": "Feature", 
      "properties": {
        "admin1_code": "", 
        "point_size": 8, 
        "name": "Manila", 
        "geonameid": 1701668, 
        "font_file": "../fonts/Arial.ttf", 
        "zoom_start": 4, 
        "font_size": 18, 
        "country_code": "PH", 
        "capital": "yes", 
        "asciiname": "Manila", 
        "justified": "left", 
        "population": 10444527
      }
    }, 
    {
      "geometry": {
        "type": "Point", 
        "coordinates": [
          37.791341249999974, 
          55.806590772755442
        ]
      }, 
      "type": "Feature", 
      "properties": {
        "admin1_code": "", 
        "point_size": 8, 
        "name": "Moscow", 
        "geonameid": 524901, 
        "font_file": "../fonts/Arial.ttf", 
        "zoom_start": 4, 
        "font_size": 18, 
        "country_code": "RU", 
        "capital": "yes", 
        "asciiname": "Moscow", 
        "justified": "left", 
        "population": 10381222
      }
    }, 
    {
      "geometry": {
        "type": "Point", 
        "coordinates": [
          90.58322124999998, 
          23.798888858983943
        ]
      }, 
      "type": "Feature", 
      "properties": {
        "admin1_code": "", 
        "point_size": 8, 
        "name": "Dhaka", 
        "geonameid": 1185241, 
        "font_file": "../fonts/Arial.ttf", 
        "zoom_start": 4, 
        "font_size": 18, 
        "country_code": "BD", 
        "capital": "yes", 
        "asciiname": "Dhaka", 
        "justified": "left", 
        "population": 10356500
      }
    }, 
    {
      "geometry": {
        "type": "Point", 
        "coordinates": [
          127.15361124999997, 
          37.644851552683839
        ]
      }, 
      "type": "Feature", 
      "properties": {
        "admin1_code": "", 
        "point_size": 8, 
        "name": "Seoul", 
        "geonameid": 1835848, 
        "font_file": "../fonts/Arial.ttf", 
        "zoom_start": 4, 
        "font_size": 18, 
        "country_code": "KR", 
        "capital": "yes", 
        "asciiname": "Seoul", 
        "justified": "left", 
        "population": 10349312
      }
    }, 
    {
      "geometry": {
        "type": "Point", 
        "coordinates": [
          107.02091125, 
          -6.1184997293896286
        ]
      }, 
      "type": "Feature", 
      "properties": {
        "admin1_code": "", 
        "point_size": 8, 
        "name": "Jakarta", 
        "geonameid": 1642911, 
        "font_file": "../fonts/Arial.ttf", 
        "zoom_start": 4, 
        "font_size": 18, 
        "country_code": "ID", 
        "capital": "yes", 
        "asciiname": "Jakarta", 
        "justified": "left", 
        "population": 8540121
      }
    }, 
    {
      "geometry": {
        "type": "Point", 
        "coordinates": [
          139.75708125, 
          35.693437082010497
        ]
      }, 
      "type": "Feature", 
      "properties": {
        "admin1_code": "", 
        "point_size": 8, 
        "name": "Tokyo", 
        "geonameid": 1850147, 
        "font_file": "../fonts/Arial.ttf", 
        "zoom_start": 4, 
        "font_size": 18, 
        "country_code": "JP", 
        "capital": "yes", 
        "asciiname": "Tokyo", 
        "justified": "left", 
        "population": 8336599
      }
    }, 
    {
      "geometry": {
        "type": "Point", 
        "coordinates": [
          121.70763124999998, 
          25.135316152207498
        ]
      }, 
      "type": "Feature", 
      "properties": {
        "admin1_code": "", 
        "point_size": 8, 
        "name": "Taipei", 
        "geonameid": 1668341, 
        "font_file": "../fonts/Arial.ttf", 
        "zoom_start": 4, 
        "font_size": 18, 
        "country_code": "TW", 
        "capital": "yes", 
        "asciiname": "Taipei", 
        "justified": "left", 
        "population": 7871900
      }
    }, 
    {
      "geometry": {
        "type": "Point", 
        "coordinates": [
          116.57301125000002, 
          39.981621021398574
        ]
      }, 
      "type": "Feature", 
      "properties": {
        "admin1_code": "", 
        "point_size": 8, 
        "name": "Beijing", 
        "geonameid": 1816670, 
        "font_file": "../fonts/Arial.ttf", 
        "zoom_start": 4, 
        "font_size": 18, 
        "country_code": "CN", 
        "capital": "yes", 
        "asciiname": "Beijing", 
        "justified": "left", 
        "population": 7480601
      }
    }, 
    {
      "geometry": {
        "type": "Point", 
        "coordinates": [
          51.597291249999998, 
          35.772868842214677
        ]
      }, 
      "type": "Feature", 
      "properties": {
        "admin1_code": "", 
        "point_size": 8, 
        "name": "Tehran", 
        "geonameid": 112931, 
        "font_file": "../fonts/Arial.ttf", 
        "zoom_start": 4, 
        "font_size": 18, 
        "country_code": "IR", 
        "capital": "yes", 
        "asciiname": "Tehran", 
        "justified": "left", 
        "population": 7153309
      }
    }, 
    {
      "geometry": {
        "type": "Point", 
        "coordinates": [
          114.33347124999997, 
          22.094274301330948
        ]
      }, 
      "type": "Feature", 
      "properties": {
        "admin1_code": "", 
        "point_size": 8, 
        "name": "Hong Kong", 
        "geonameid": 1819729, 
        "font_file": "../fonts/Arial.ttf", 
        "zoom_start": 4, 
        "font_size": 18, 
        "country_code": "HK", 
        "capital": "yes", 
        "asciiname": "Hong Kong", 
        "justified": "left", 
        "population": 7012738
      }
    }, 
    {
      "geometry": {
        "type": "Point", 
        "coordinates": [
          74.519391250000012, 
          31.632072729433009
        ]
      }, 
      "type": "Feature", 
      "properties": {
        "admin1_code": "", 
        "point_size": 8, 
        "name": "Lahore", 
        "geonameid": 1172451, 
        "font_file": "../fonts/Arial.ttf", 
        "zoom_start": 5, 
        "font_size": 18, 
        "country_code": "PK", 
        "capital": "no", 
        "asciiname": "Lahore", 
        "justified": "left", 
        "population": 6310888
      }
    }, 
    {
      "geometry": {
        "type": "Point", 
        "coordinates": [
          44.576661249999994, 
          33.421310512961128
        ]
      }, 
      "type": "Feature", 
      "properties": {
        "admin1_code": "", 
        "point_size": 8, 
        "name": "Baghdad", 
        "geonameid": 98182, 
        "font_file": "../fonts/Arial.ttf", 
        "zoom_start": 4, 
        "font_size": 18, 
        "country_code": "IQ", 
        "capital": "yes", 
        "asciiname": "Baghdad", 
        "justified": "left", 
        "population": 5672513
      }
    }, 
    {
      "geometry": {
        "type": "Point", 
        "coordinates": [
          100.69245125000003, 
          13.843890176387333
        ]
      }, 
      "type": "Feature", 
      "properties": {
        "admin1_code": "", 
        "point_size": 8, 
        "name": "Bangkok", 
        "geonameid": 1609350, 
        "font_file": "../fonts/Arial.ttf", 
        "zoom_start": 4, 
        "font_size": 18, 
        "country_code": "TH", 
        "capital": "yes", 
        "asciiname": "Bangkok", 
        "justified": "left", 
        "population": 5104476
      }
    }, 
    {
      "geometry": {
        "type": "Point", 
        "coordinates": [
          77.779071250000001, 
          13.070422919621091
        ]
      }, 
      "type": "Feature", 
      "properties": {
        "admin1_code": "", 
        "point_size": 8, 
        "name": "Bangalore", 
        "geonameid": 1277333, 
        "font_file": "../fonts/Arial.ttf", 
        "zoom_start": 4, 
        "font_size": 18, 
        "country_code": "IN", 
        "capital": "no", 
        "asciiname": "Bengaluru", 
        "justified": "left", 
        "population": 5104047
      }
    }, 
    {
      "geometry": {
        "type": "Point", 
        "coordinates": [
          88.545501250000001, 
          22.658966359476565
        ]
      }, 
      "type": "Feature", 
      "properties": {
        "admin1_code": "", 
        "point_size": 8, 
        "name": "Kolkata", 
        "geonameid": 1275004, 
        "font_file": "../fonts/Arial.ttf", 
        "zoom_start": 4, 
        "font_size": 18, 
        "country_code": "IN", 
        "capital": "no", 
        "asciiname": "Calcutta", 
        "justified": "left", 
        "population": 4631392
      }
    }, 
    {
      "geometry": {
        "type": "Point", 
        "coordinates": [
          96.331891250000027, 
          16.897808162145786
        ]
      }, 
      "type": "Feature", 
      "properties": {
        "admin1_code": "", 
        "point_size": 8, 
        "name": "Yangon", 
        "geonameid": 1298824, 
        "font_file": "../fonts/Arial.ttf", 
        "zoom_start": 5, 
        "font_size": 18, 
        "country_code": "MM", 
        "capital": "no", 
        "asciiname": "Rangoon", 
        "justified": "left", 
        "population": 4477638
      }
    }, 
    {
      "geometry": {
        "type": "Point", 
        "coordinates": [
          80.45425124999997, 
          13.18199030973655
        ]
      }, 
      "type": "Feature", 
      "properties": {
        "admin1_code": "", 
        "point_size": 8, 
        "name": "Chennai", 
        "geonameid": 1264527, 
        "font_file": "../fonts/Arial.ttf", 
        "zoom_start": 4, 
        "font_size": 18, 
        "country_code": "IN", 
        "capital": "no", 
        "asciiname": "Chennai", 
        "justified": "left", 
        "population": 4328063
      }
    }, 
    {
      "geometry": {
        "type": "Point", 
        "coordinates": [
          46.897631249999975, 
          24.775541954535719
        ]
      }, 
      "type": "Feature", 
      "properties": {
        "admin1_code": "", 
        "point_size": 8, 
        "name": "Riyadh", 
        "geonameid": 108410, 
        "font_file": "../fonts/Arial.ttf", 
        "zoom_start": 4, 
        "font_size": 18, 
        "country_code": "SA", 
        "capital": "yes", 
        "asciiname": "Riyadh", 
        "justified": "left", 
        "population": 4205961
      }
    }, 
    {
      "geometry": {
        "type": "Point", 
        "coordinates": [
          114.44245124999999, 
          30.66652483858245
        ]
      }, 
      "type": "Feature", 
      "properties": {
        "admin1_code": "", 
        "point_size": 8, 
        "name": "Wuhan", 
        "geonameid": 1791247, 
        "font_file": "../fonts/Arial.ttf", 
        "zoom_start": 5, 
        "font_size": 18, 
        "country_code": "CN", 
        "capital": "no", 
        "asciiname": "Wuhan", 
        "justified": "left", 
        "population": 4184206
      }
    }, 
    {
      "geometry": {
        "type": "Point", 
        "coordinates": [
          30.439951250000018, 
          59.942898634536533
        ]
      }, 
      "type": "Feature", 
      "properties": {
        "admin1_code": "", 
        "point_size": 8, 
        "name": "St. Petersburg", 
        "geonameid": 498817, 
        "font_file": "../fonts/Arial.ttf", 
        "zoom_start": 4, 
        "font_size": 18, 
        "country_code": "RU", 
        "capital": "no", 
        "asciiname": "Saint Petersburg", 
        "justified": "left", 
        "population": 4039745
      }
    }, 
    {
      "geometry": {
        "type": "Point", 
        "coordinates": [
          106.72856124999997, 
          29.646838477023312
        ]
      }, 
      "type": "Feature", 
      "properties": {
        "admin1_code": "", 
        "point_size": 8, 
        "name": "Chongqing", 
        "geonameid": 1814906, 
        "font_file": "../fonts/Arial.ttf", 
        "zoom_start": 4, 
        "font_size": 18, 
        "country_code": "CN", 
        "capital": "no", 
        "asciiname": "Chongqing", 
        "justified": "left", 
        "population": 3967028
      }
    }, 
    {
      "geometry": {
        "type": "Point", 
        "coordinates": [
          104.24245124999997, 
          30.749793144293996
        ]
      }, 
      "type": "Feature", 
      "properties": {
        "admin1_code": "", 
        "point_size": 8, 
        "name": "Chengdu", 
        "geonameid": 1815286, 
        "font_file": "../fonts/Arial.ttf", 
        "zoom_start": 5, 
        "font_size": 18, 
        "country_code": "CN", 
        "capital": "no", 
        "asciiname": "Chengdu", 
        "justified": "left", 
        "population": 3950437
      }
    }, 
    {
      "geometry": {
        "type": "Point", 
        "coordinates": [
          92.012171250000009, 
          22.422459103564329
        ]
      }, 
      "type": "Feature", 
      "properties": {
        "admin1_code": "", 
        "point_size": 8, 
        "name": "Chittagong", 
        "geonameid": 1205733, 
        "font_file": "../fonts/Arial.ttf", 
        "zoom_start": 5, 
        "font_size": 18, 
        "country_code": "BD", 
        "capital": "no", 
        "asciiname": "Chittagong", 
        "justified": "left", 
        "population": 3920222
      }
    }, 
    {
      "geometry": {
        "type": "Point", 
        "coordinates": [
          117.35245124999996, 
          39.21716303229902
        ]
      }, 
      "type": "Feature", 
      "properties": {
        "admin1_code": "", 
        "point_size": 8, 
        "name": "Tianjin", 
        "geonameid": 1792947, 
        "font_file": "../fonts/Arial.ttf", 
        "zoom_start": 5, 
        "font_size": 18, 
        "country_code": "CN", 
        "capital": "no", 
        "asciiname": "Tianjin", 
        "justified": "left", 
        "population": 3766207
      }
    }, 
    {
      "geometry": {
        "type": "Point", 
        "coordinates": [
          72.792451249999971, 
          23.122272732038844
        ]
      }, 
      "type": "Feature", 
      "properties": {
        "admin1_code": "", 
        "point_size": 8, 
        "name": "Ahmadabad", 
        "geonameid": 1279233, 
        "font_file": "../fonts/Arial.ttf", 
        "zoom_start": 5, 
        "font_size": 18, 
        "country_code": "IN", 
        "capital": "no", 
        "asciiname": "Ahmadabad", 
        "justified": "left", 
        "population": 3719710
      }
    }, 
    {
      "geometry": {
        "type": "Point", 
        "coordinates": [
          129.21606124999997, 
          35.181837374884637
        ]
      }, 
      "type": "Feature", 
      "properties": {
        "admin1_code": "", 
        "point_size": 8, 
        "name": "Pusan", 
        "geonameid": 1838524, 
        "font_file": "../fonts/Arial.ttf", 
        "zoom_start": 5, 
        "font_size": 18, 
        "country_code": "KR", 
        "capital": "no", 
        "asciiname": "Pusan", 
        "justified": "left", 
        "population": 3678555
      }
    }, 
    {
      "geometry": {
        "type": "Point", 
        "coordinates": [
          78.650221249999987, 
          17.467524838843985
        ]
      }, 
      "type": "Feature", 
      "properties": {
        "admin1_code": "", 
        "point_size": 8, 
        "name": "Hyderabad", 
        "geonameid": 1269843, 
        "font_file": "../fonts/Arial.ttf", 
        "zoom_start": 4, 
        "font_size": 18, 
        "country_code": "IN", 
        "capital": "no", 
        "asciiname": "Hyderabad", 
        "justified": "left", 
        "population": 3597816
      }
    }, 
    {
      "geometry": {
        "type": "Point", 
        "coordinates": [
          139.81828124999998, 
          35.279345151435521
        ]
      }, 
      "type": "Feature", 
      "properties": {
        "admin1_code": "", 
        "point_size": 8, 
        "name": "Yokohama", 
        "geonameid": 1848354, 
        "font_file": "../fonts/Arial.ttf", 
        "zoom_start": 6, 
        "font_size": 18, 
        "country_code": "JP", 
        "capital": "no", 
        "asciiname": "Yokohama-shi", 
        "justified": "left", 
        "population": 3574443
      }
    }, 
    {
      "geometry": {
        "type": "Point", 
        "coordinates": [
          104.02585125000003, 
          1.0831714220338087
        ]
      }, 
      "type": "Feature", 
      "properties": {
        "admin1_code": "", 
        "point_size": 8, 
        "name": "Singapore", 
        "geonameid": 1880252, 
        "font_file": "../fonts/Arial.ttf", 
        "zoom_start": 4, 
        "font_size": 18, 
        "country_code": "SG", 
        "capital": "yes", 
        "asciiname": "Singapore", 
        "justified": "left", 
        "population": 3547809
      }
    }, 
    {
      "geometry": {
        "type": "Point", 
        "coordinates": [
          33.030051249999993, 
          39.993977625581174
        ]
      }, 
      "type": "Feature", 
      "properties": {
        "admin1_code": "", 
        "point_size": 8, 
        "name": "Ankara", 
        "geonameid": 323786, 
        "font_file": "../fonts/Arial.ttf", 
        "zoom_start": 5, 
        "font_size": 18, 
        "country_code": "TR", 
        "capital": "yes", 
        "asciiname": "Ankara", 
        "justified": "left", 
        "population": 3517182
      }
    }, 
    {
      "geometry": {
        "type": "Point", 
        "coordinates": [
          123.60856124999998, 
          41.864260603922766
        ]
      }, 
      "type": "Feature", 
      "properties": {
        "admin1_code": "", 
        "point_size": 8, 
        "name": "Shenyang", 
        "geonameid": 2034937, 
        "font_file": "../fonts/Arial.ttf", 
        "zoom_start": 5, 
        "font_size": 18, 
        "country_code": "CN", 
        "capital": "no", 
        "asciiname": "Shenyang", 
        "justified": "left", 
        "population": 3512192
      }
    }, 
    {
      "geometry": {
        "type": "Point", 
        "coordinates": [
          106.84245124999998, 
          10.844968008197956
        ]
      }, 
      "type": "Feature", 
      "properties": {
        "admin1_code": "", 
        "point_size": 8, 
        "name": "Ho Chi Minh City", 
        "geonameid": 1566083, 
        "font_file": "../fonts/Arial.ttf", 
        "zoom_start": 4, 
        "font_size": 18, 
        "country_code": "VN", 
        "capital": "no", 
        "asciiname": "Thanh pho Ho Chi Minh", 
        "justified": "left", 
        "population": 3467331
      }
    }, 
    {
      "geometry": {
        "type": "Point", 
        "coordinates": [
          126.82578125000002, 
          45.817421394614783
        ]
      }, 
      "type": "Feature", 
      "properties": {
        "admin1_code": "", 
        "point_size": 8, 
        "name": "Harbin", 
        "geonameid": 2037013, 
        "font_file": "../fonts/Arial.ttf", 
        "zoom_start": 5, 
        "font_size": 18, 
        "country_code": "CN", 
        "capital": "no", 
        "asciiname": "Harbin", 
        "justified": "left", 
        "population": 3229883
      }
    }, 
    {
      "geometry": {
        "type": "Point", 
        "coordinates": [
          109.10439124999998, 
          34.338198562898967
        ]
      }, 
      "type": "Feature", 
      "properties": {
        "admin1_code": "", 
        "point_size": 8, 
        "name": "Xi\u2019an", 
        "geonameid": 1790630, 
        "font_file": "../fonts/Arial.ttf", 
        "zoom_start": 5, 
        "font_size": 18, 
        "country_code": "CN", 
        "capital": "no", 
        "asciiname": "Xi'an", 
        "justified": "left", 
        "population": 3225812
      }
    }, 
    {
      "geometry": {
        "type": "Point", 
        "coordinates": [
          125.93010124999996, 
          39.108908360279159
        ]
      }, 
      "type": "Feature", 
      "properties": {
        "admin1_code": "", 
        "point_size": 8, 
        "name": "Pyongyang", 
        "geonameid": 1871859, 
        "font_file": "../fonts/Arial.ttf", 
        "zoom_start": 5, 
        "font_size": 18, 
        "country_code": "KP", 
        "capital": "yes", 
        "asciiname": "Pyongyang", 
        "justified": "left", 
        "population": 3222000
      }
    }, 
    {
      "geometry": {
        "type": "Point", 
        "coordinates": [
          113.42578125000001, 
          23.205557533541747
        ]
      }, 
      "type": "Feature", 
      "properties": {
        "admin1_code": "", 
        "point_size": 8, 
        "name": "Guangzhou", 
        "geonameid": 1809858, 
        "font_file": "../fonts/Arial.ttf", 
        "zoom_start": 4, 
        "font_size": 18, 
        "country_code": "CN", 
        "capital": "no", 
        "asciiname": "Guangzhou", 
        "justified": "left", 
        "population": 3152825
      }
    }, 
    {
      "geometry": {
        "type": "Point", 
        "coordinates": [
          118.95356124999999, 
          32.14356712210116
        ]
      }, 
      "type": "Feature", 
      "properties": {
        "admin1_code": "", 
        "point_size": 8, 
        "name": "Nanjing", 
        "geonameid": 1799962, 
        "font_file": "../fonts/Arial.ttf", 
        "zoom_start": 5, 
        "font_size": 18, 
        "country_code": "CN", 
        "capital": "no", 
        "asciiname": "Nanjing", 
        "justified": "left", 
        "population": 3087010
      }
    }, 
    {
      "geometry": {
        "type": "Point", 
        "coordinates": [
          69.348111250000017, 
          34.607741264967316
        ]
      }, 
      "type": "Feature", 
      "properties": {
        "admin1_code": "", 
        "point_size": 8, 
        "name": "Kabul", 
        "geonameid": 1138958, 
        "font_file": "../fonts/Arial.ttf", 
        "zoom_start": 5, 
        "font_size": 18, 
        "country_code": "AF", 
        "capital": "yes", 
        "asciiname": "Kabul", 
        "justified": "left", 
        "population": 3043532
      }
    }, 
    {
      "geometry": {
        "type": "Point", 
        "coordinates": [
          114.24408125000002, 
          22.634802035442977
        ]
      }, 
      "type": "Feature", 
      "properties": {
        "admin1_code": "", 
        "point_size": 8, 
        "name": "Shenzhen", 
        "geonameid": 1795565, 
        "font_file": "../fonts/Arial.ttf", 
        "zoom_start": 6, 
        "font_size": 18, 
        "country_code": "CN", 
        "capital": "no", 
        "asciiname": "Shenzhen", 
        "justified": "left", 
        "population": 3000000
      }
    }, 
    {
      "geometry": {
        "type": "Point", 
        "coordinates": [
          74.031131250000016, 
          18.611218549993964
        ]
      }, 
      "type": "Feature", 
      "properties": {
        "admin1_code": "", 
        "point_size": 8, 
        "name": "Pune", 
        "geonameid": 1259229, 
        "font_file": "../fonts/Arial.ttf", 
        "zoom_start": 5, 
        "font_size": 18, 
        "country_code": "IN", 
        "capital": "no", 
        "asciiname": "Pune", 
        "justified": "left", 
        "population": 2935744
      }
    }, 
    {
      "geometry": {
        "type": "Point", 
        "coordinates": [
          73.009111250000004, 
          21.256799599220333
        ]
      }, 
      "type": "Feature", 
      "properties": {
        "admin1_code": "", 
        "point_size": 8, 
        "name": "Surat", 
        "geonameid": 1255364, 
        "font_file": "../fonts/Arial.ttf", 
        "zoom_start": 5, 
        "font_size": 18, 
        "country_code": "IN", 
        "capital": "no", 
        "asciiname": "Surat", 
        "justified": "left", 
        "population": 2894504
      }
    }, 
    {
      "geometry": {
        "type": "Point", 
        "coordinates": [
          39.343466113880432, 
          21.72237004184473
        ]
      }, 
      "type": "Feature", 
      "properties": {
        "admin1_code": "", 
        "point_size": 8, 
        "name": "Jeddah", 
        "geonameid": 105343, 
        "font_file": "../fonts/Arial.ttf", 
        "zoom_start": 5, 
        "font_size": 18, 
        "country_code": "SA", 
        "capital": "no", 
        "asciiname": "Jiddah", 
        "justified": "left", 
        "population": 2867446
      }
    }, 
    {
      "geometry": {
        "type": "Point", 
        "coordinates": [
          80.525781250000023, 
          26.281625735727111
        ]
      }, 
      "type": "Feature", 
      "properties": {
        "admin1_code": "", 
        "point_size": 8, 
        "name": "Kanpur", 
        "geonameid": 1267995, 
        "font_file": "../fonts/Arial.ttf", 
        "zoom_start": 5, 
        "font_size": 18, 
        "country_code": "IN", 
        "capital": "no", 
        "asciiname": "Kanpur", 
        "justified": "left", 
        "population": 2823249
      }
    }, 
    {
      "geometry": {
        "type": "Point", 
        "coordinates": [
          112.73606124999995, 
          37.945720532412437
        ]
      }, 
      "type": "Feature", 
      "properties": {
        "admin1_code": "", 
        "point_size": 8, 
        "name": "Taiyuan", 
        "geonameid": 1793511, 
        "font_file": "../fonts/Arial.ttf", 
        "zoom_start": 5, 
        "font_size": 18, 
        "country_code": "CN", 
        "capital": "no", 
        "asciiname": "Taiyuan", 
        "justified": "left", 
        "population": 2722475
      }
    }, 
    {
      "geometry": {
        "type": "Point", 
        "coordinates": [
          75.992451249999988, 
          27.002843027425996
        ]
      }, 
      "type": "Feature", 
      "properties": {
        "admin1_code": "", 
        "point_size": 8, 
        "name": "Jaipur", 
        "geonameid": 1269515, 
        "font_file": "../fonts/Arial.ttf", 
        "zoom_start": 5, 
        "font_size": 18, 
        "country_code": "IN", 
        "capital": "no", 
        "asciiname": "Jaipur", 
        "justified": "left", 
        "population": 2711758
      }
    }, 
    {
      "geometry": {
        "type": "Point", 
        "coordinates": [
          135.67796125000001, 
          34.523744990311258
        ]
      }, 
      "type": "Feature", 
      "properties": {
        "admin1_code": "", 
        "point_size": 8, 
        "name": "Osaka", 
        "geonameid": 1853909, 
        "font_file": "../fonts/Arial.ttf", 
        "zoom_start": 4, 
        "font_size": 18, 
        "country_code": "JP", 
        "capital": "no", 
        "asciiname": "Osaka-shi", 
        "justified": "left", 
        "population": 2592413
      }
    }, 
    {
      "geometry": {
        "type": "Point", 
        "coordinates": [
          128.76689124999996, 
          35.948585226181443
        ]
      }, 
      "type": "Feature", 
      "properties": {
        "admin1_code": "", 
        "point_size": 8, 
        "name": "Daegu", 
        "geonameid": 1835329, 
        "font_file": "../fonts/Arial.ttf", 
        "zoom_start": 6, 
        "font_size": 18, 
        "country_code": "KR", 
        "capital": "no", 
        "asciiname": "Taegu", 
        "justified": "left", 
        "population": 2566540
      }
    }, 
    {
      "geometry": {
        "type": "Point", 
        "coordinates": [
          125.49856124999998, 
          43.949645298768878
        ]
      }, 
      "type": "Feature", 
      "properties": {
        "admin1_code": "", 
        "point_size": 8, 
        "name": "Changchun", 
        "geonameid": 2038180, 
        "font_file": "../fonts/Arial.ttf", 
        "zoom_start": 5, 
        "font_size": 18, 
        "country_code": "CN", 
        "capital": "no", 
        "asciiname": "Changchun", 
        "justified": "left", 
        "population": 2537421
      }
    }, 
    {
      "geometry": {
        "type": "Point", 
        "coordinates": [
          73.207626113880437, 
          31.004045895431812
        ]
      }, 
      "type": "Feature", 
      "properties": {
        "admin1_code": "", 
        "point_size": 8, 
        "name": "Faisalabad", 
        "geonameid": 1179400, 
        "font_file": "../fonts/Arial.ttf", 
        "zoom_start": 5, 
        "font_size": 18, 
        "country_code": "PK", 
        "capital": "no", 
        "asciiname": "Faisalabad", 
        "justified": "left", 
        "population": 2506595
      }
    }, 
    {
      "geometry": {
        "type": "Point", 
        "coordinates": [
          27.314161249999991, 
          38.488444175654273
        ]
      }, 
      "type": "Feature", 
      "properties": {
        "admin1_code": "", 
        "point_size": 8, 
        "name": "Izmir", 
        "geonameid": 311046, 
        "font_file": "../fonts/Arial.ttf", 
        "zoom_start": 5, 
        "font_size": 18, 
        "country_code": "TR", 
        "capital": "no", 
        "asciiname": "Izmir", 
        "justified": "left", 
        "population": 2500603
      }
    }, 
    {
      "geometry": {
        "type": "Point", 
        "coordinates": [
          81.092451249999982, 
          26.936223952046021
        ]
      }, 
      "type": "Feature", 
      "properties": {
        "admin1_code": "", 
        "point_size": 8, 
        "name": "Lucknow", 
        "geonameid": 1264733, 
        "font_file": "../fonts/Arial.ttf", 
        "zoom_start": 5, 
        "font_size": 18, 
        "country_code": "IN", 
        "capital": "no", 
        "asciiname": "Lucknow", 
        "justified": "left", 
        "population": 2472011
      }
    }, 
    {
      "geometry": {
        "type": "Point", 
        "coordinates": [
          112.92661125000001, 
          -7.1532529284982305
        ]
      }, 
      "type": "Feature", 
      "properties": {
        "admin1_code": "", 
        "point_size": 8, 
        "name": "Surabaya", 
        "geonameid": 1625822, 
        "font_file": "../fonts/Arial.ttf", 
        "zoom_start": 5, 
        "font_size": 18, 
        "country_code": "ID", 
        "capital": "no", 
        "asciiname": "Surabaya", 
        "justified": "left", 
        "population": 2374658
      }
    }, 
    {
      "geometry": {
        "type": "Point", 
        "coordinates": [
          59.781981250000001, 
          36.374880963901639
        ]
      }, 
      "type": "Feature", 
      "properties": {
        "admin1_code": "", 
        "point_size": 8, 
        "name": "Mashhad", 
        "geonameid": 124665, 
        "font_file": "../fonts/Arial.ttf", 
        "zoom_start": 5, 
        "font_size": 18, 
        "country_code": "IR", 
        "capital": "no", 
        "asciiname": "Mashhad", 
        "justified": "left", 
        "population": 2307177
      }
    }, 
    {
      "geometry": {
        "type": "Point", 
        "coordinates": [
          79.275781249999952, 
          21.240139769669785
        ]
      }, 
      "type": "Feature", 
      "properties": {
        "admin1_code": "", 
        "point_size": 8, 
        "name": "Nagpur", 
        "geonameid": 1262180, 
        "font_file": "../fonts/Arial.ttf", 
        "zoom_start": 5, 
        "font_size": 18, 
        "country_code": "IN", 
        "capital": "no", 
        "asciiname": "Nagpur", 
        "justified": "left", 
        "population": 2228018
      }
    }, 
    {
      "geometry": {
        "type": "Point", 
        "coordinates": [
          137.08219124999994, 
          35.260450908251578
        ]
      }, 
      "type": "Feature", 
      "properties": {
        "admin1_code": "", 
        "point_size": 8, 
        "name": "Nagoya", 
        "geonameid": 1856057, 
        "font_file": "../fonts/Arial.ttf", 
        "zoom_start": 5, 
        "font_size": 18, 
        "country_code": "JP", 
        "capital": "no", 
        "asciiname": "Nagoya-shi", 
        "justified": "left", 
        "population": 2191279
      }
    }, 
    {
      "geometry": {
        "type": "Point", 
        "coordinates": [
          117.17300125000001, 
          36.745838261878049
        ]
      }, 
      "type": "Feature", 
      "properties": {
        "admin1_code": "", 
        "point_size": 8, 
        "name": "Jinan", 
        "geonameid": 1805753, 
        "font_file": "../fonts/Arial.ttf", 
        "zoom_start": 5, 
        "font_size": 18, 
        "country_code": "CN", 
        "capital": "no", 
        "asciiname": "Jinan", 
        "justified": "left", 
        "population": 2069266
      }
    }, 
    {
      "geometry": {
        "type": "Point", 
        "coordinates": [
          121.77800124999996, 
          38.987407480307361
        ]
      }, 
      "type": "Feature", 
      "properties": {
        "admin1_code": "", 
        "point_size": 8, 
        "name": "Dalian", 
        "geonameid": 1814087, 
        "font_file": "../fonts/Arial.ttf", 
        "zoom_start": 5, 
        "font_size": 18, 
        "country_code": "CN", 
        "capital": "no", 
        "asciiname": "Dalian", 
        "justified": "left", 
        "population": 2035307
      }
    }, 
    {
      "geometry": {
        "type": "Point", 
        "coordinates": [
          77.125781250000003, 
          43.320377967988016
        ]
      }, 
      "type": "Feature", 
      "properties": {
        "admin1_code": "", 
        "point_size": 8, 
        "name": "Almaty", 
        "geonameid": 1526384, 
        "font_file": "../fonts/Arial.ttf", 
        "zoom_start": 4, 
        "font_size": 18, 
        "country_code": "KZ", 
        "capital": "no", 
        "asciiname": "Almaty", 
        "justified": "left", 
        "population": 2000900
      }
    }, 
    {
      "geometry": {
        "type": "Point", 
        "coordinates": [
          69.392051249999994, 
          41.337280894084437
        ]
      }, 
      "type": "Feature", 
      "properties": {
        "admin1_code": "", 
        "point_size": 8, 
        "name": "Tashkent", 
        "geonameid": 1512569, 
        "font_file": "../fonts/Arial.ttf", 
        "zoom_start": 5, 
        "font_size": 18, 
        "country_code": "UZ", 
        "capital": "yes", 
        "asciiname": "Tashkent", 
        "justified": "left", 
        "population": 1978028
      }
    }, 
    {
      "geometry": {
        "type": "Point", 
        "coordinates": [
          44.382451249999981, 
          15.447927837299304
        ]
      }, 
      "type": "Feature", 
      "properties": {
        "admin1_code": "", 
        "point_size": 8, 
        "name": "Sanaa", 
        "geonameid": 71137, 
        "font_file": "../fonts/Arial.ttf", 
        "zoom_start": 5, 
        "font_size": 18, 
        "country_code": "YE", 
        "capital": "yes", 
        "asciiname": "Sanaa", 
        "justified": "left", 
        "population": 1937451
      }
    }, 
    {
      "geometry": {
        "type": "Point", 
        "coordinates": [
          35.670201250000012, 
          33.969157966758679
        ]
      }, 
      "type": "Feature", 
      "properties": {
        "admin1_code": "", 
        "point_size": 8, 
        "name": "Beirut", 
        "geonameid": 276781, 
        "font_file": "../fonts/Arial.ttf", 
        "zoom_start": 4, 
        "font_size": 18, 
        "country_code": "LB", 
        "capital": "yes", 
        "asciiname": "Beirut", 
        "justified": "left", 
        "population": 1916100
      }
    }, 
    {
      "geometry": {
        "type": "Point", 
        "coordinates": [
          141.52272124999996, 
          43.134762463843863
        ]
      }, 
      "type": "Feature", 
      "properties": {
        "admin1_code": "", 
        "point_size": 8, 
        "name": "Sapporo", 
        "geonameid": 2128295, 
        "font_file": "../fonts/Arial.ttf", 
        "zoom_start": 5, 
        "font_size": 18, 
        "country_code": "JP", 
        "capital": "no", 
        "asciiname": "Sapporo-shi", 
        "justified": "left", 
        "population": 1883027
      }
    }, 
    {
      "geometry": {
        "type": "Point", 
        "coordinates": [
          116.05911124999997, 
          28.768111354120698
        ]
      }, 
      "type": "Feature", 
      "properties": {
        "admin1_code": "", 
        "point_size": 8, 
        "name": "Nanchang", 
        "geonameid": 1800163, 
        "font_file": "../fonts/Arial.ttf", 
        "zoom_start": 5, 
        "font_size": 18, 
        "country_code": "CN", 
        "capital": "no", 
        "asciiname": "Nanchang", 
        "justified": "left", 
        "population": 1871351
      }
    }, 
    {
      "geometry": {
        "type": "Point", 
        "coordinates": [
          76.009081249999994, 
          22.807069934158978
        ]
      }, 
      "type": "Feature", 
      "properties": {
        "admin1_code": "", 
        "point_size": 8, 
        "name": "Indore", 
        "geonameid": 1269743, 
        "font_file": "../fonts/Arial.ttf", 
        "zoom_start": 6, 
        "font_size": 18, 
        "country_code": "IN", 
        "capital": "no", 
        "asciiname": "Indore", 
        "justified": "left", 
        "population": 1837041
      }
    }, 
    {
      "geometry": {
        "type": "Point", 
        "coordinates": [
          98.842451249999968, 
          3.6798155409000208
        ]
      }, 
      "type": "Feature", 
      "properties": {
        "admin1_code": "", 
        "point_size": 8, 
        "name": "Medan", 
        "geonameid": 1214520, 
        "font_file": "../fonts/Arial.ttf", 
        "zoom_start": 5, 
        "font_size": 18, 
        "country_code": "ID", 
        "capital": "no", 
        "asciiname": "Medan", 
        "justified": "left", 
        "population": 1750971
      }
    }, 
    {
      "geometry": {
        "type": "Point", 
        "coordinates": [
          107.79439125000003, 
          -6.8079016297652757
        ]
      }, 
      "type": "Feature", 
      "properties": {
        "admin1_code": "", 
        "point_size": 8, 
        "name": "Bandung", 
        "geonameid": 1650357, 
        "font_file": "../fonts/Arial.ttf", 
        "zoom_start": 5, 
        "font_size": 18, 
        "country_code": "ID", 
        "capital": "no", 
        "asciiname": "Bandung", 
        "justified": "left", 
        "population": 1699719
      }
    }, 
    {
      "geometry": {
        "type": "Point", 
        "coordinates": [
          120.54772125000001, 
          36.176688749218556
        ]
      }, 
      "type": "Feature", 
      "properties": {
        "admin1_code": "", 
        "point_size": 8, 
        "name": "Qingdao", 
        "geonameid": 1797929, 
        "font_file": "../fonts/Arial.ttf", 
        "zoom_start": 5, 
        "font_size": 18, 
        "country_code": "CN", 
        "capital": "no", 
        "asciiname": "Qingdao", 
        "justified": "left", 
        "population": 1642245
      }
    }, 
    {
      "geometry": {
        "type": "Point", 
        "coordinates": [
          37.33439125000001, 
          36.280755013118707
        ]
      }, 
      "type": "Feature", 
      "properties": {
        "admin1_code": "", 
        "point_size": 8, 
        "name": "Aleppo", 
        "geonameid": 170063, 
        "font_file": "../fonts/Arial.ttf", 
        "zoom_start": 5, 
        "font_size": 18, 
        "country_code": "SY", 
        "capital": "no", 
        "asciiname": "Aleppo", 
        "justified": "left", 
        "population": 1602264
      }
    }, 
    {
      "geometry": {
        "type": "Point", 
        "coordinates": [
          105.09245124999998, 
          11.644705915350652
        ]
      }, 
      "type": "Feature", 
      "properties": {
        "admin1_code": "", 
        "point_size": 8, 
        "name": "Phnom Penh", 
        "geonameid": 1821306, 
        "font_file": "../fonts/Arial.ttf", 
        "zoom_start": 5, 
        "font_size": 18, 
        "country_code": "KH", 
        "capital": "yes", 
        "asciiname": "Phnom Penh", 
        "justified": "left", 
        "population": 1573544
      }
    }, 
    {
      "geometry": {
        "type": "Point", 
        "coordinates": [
          36.467061249999986, 
          33.46438656319053
        ]
      }, 
      "type": "Feature", 
      "properties": {
        "admin1_code": "", 
        "point_size": 8, 
        "name": "Damascus", 
        "geonameid": 170654, 
        "font_file": "../fonts/Arial.ttf", 
        "zoom_start": 5, 
        "font_size": 18, 
        "country_code": "SY", 
        "capital": "yes", 
        "asciiname": "Damascus", 
        "justified": "left", 
        "population": 1569394
      }
    }, 
    {
      "geometry": {
        "type": "Point", 
        "coordinates": [
          51.853391250000001, 
          32.73857890174272
        ]
      }, 
      "type": "Feature", 
      "properties": {
        "admin1_code": "", 
        "point_size": 8, 
        "name": "Esfahan", 
        "geonameid": 418863, 
        "font_file": "../fonts/Arial.ttf", 
        "zoom_start": 5, 
        "font_size": 18, 
        "country_code": "IR", 
        "capital": "no", 
        "asciiname": "Esfehan", 
        "justified": "left", 
        "population": 1547164
      }
    }, 
    {
      "geometry": {
        "type": "Point", 
        "coordinates": [
          135.00721874999996, 
          34.646121210585555
        ]
      }, 
      "type": "Feature", 
      "properties": {
        "admin1_code": "", 
        "point_size": 8, 
        "name": "Kobe", 
        "geonameid": 1859171, 
        "font_file": "../fonts/Arial.ttf", 
        "zoom_start": 6, 
        "font_size": 18, 
        "country_code": "JP", 
        "capital": "no", 
        "asciiname": "Kobe-shi", 
        "justified": "right", 
        "population": 1528478
      }
    }, 
    {
      "geometry": {
        "type": "Point", 
        "coordinates": [
          120.48911124999995, 
          22.705476142762389
        ]
      }, 
      "type": "Feature", 
      "properties": {
        "admin1_code": "", 
        "point_size": 8, 
        "name": "Kaohsiung", 
        "geonameid": 1673820, 
        "font_file": "../fonts/Arial.ttf", 
        "zoom_start": 5, 
        "font_size": 18, 
        "country_code": "TW", 
        "capital": "no", 
        "asciiname": "Kaohsiung", 
        "justified": "left", 
        "population": 1519711
      }
    }, 
    {
      "geometry": {
        "type": "Point", 
        "coordinates": [
          87.759111249999989, 
          43.869738803895324
        ]
      }, 
      "type": "Feature", 
      "properties": {
        "admin1_code": "", 
        "point_size": 8, 
        "name": "Urumqi", 
        "geonameid": 1529102, 
        "font_file": "../fonts/Arial.ttf", 
        "zoom_start": 5, 
        "font_size": 18, 
        "country_code": "CN", 
        "capital": "no", 
        "asciiname": "Urumqi", 
        "justified": "left", 
        "population": 1508225
      }
    }, 
    {
      "geometry": {
        "type": "Point", 
        "coordinates": [
          135.57806874999994, 
          35.100206618601661
        ]
      }, 
      "type": "Feature", 
      "properties": {
        "admin1_code": "", 
        "point_size": 8, 
        "name": "Kyoto", 
        "geonameid": 1857910, 
        "font_file": "../fonts/Arial.ttf", 
        "zoom_start": 6, 
        "font_size": 18, 
        "country_code": "JP", 
        "capital": "no", 
        "asciiname": "Kyoto", 
        "justified": "right", 
        "population": 1459640
      }
    }, 
    {
      "geometry": {
        "type": "Point", 
        "coordinates": [
          101.86231125000003, 
          3.2377299202660725
        ]
      }, 
      "type": "Feature", 
      "properties": {
        "admin1_code": "", 
        "point_size": 8, 
        "name": "Kuala Lumpur", 
        "geonameid": 1735161, 
        "font_file": "../fonts/Arial.ttf", 
        "zoom_start": 4, 
        "font_size": 18, 
        "country_code": "MY", 
        "capital": "yes", 
        "asciiname": "Kuala Lumpur", 
        "justified": "left", 
        "population": 1453975
      }
    }, 
    {
      "geometry": {
        "type": "Point", 
        "coordinates": [
          85.496381250000013, 
          27.787254658396837
        ]
      }, 
      "type": "Feature", 
      "properties": {
        "admin1_code": "", 
        "point_size": 8, 
        "name": "Kathmandu", 
        "geonameid": 1283240, 
        "font_file": "../fonts/Arial.ttf", 
        "zoom_start": 5, 
        "font_size": 18, 
        "country_code": "NP", 
        "capital": "yes", 
        "asciiname": "Kathmandu", 
        "justified": "left", 
        "population": 1442271
      }
    }, 
    {
      "geometry": {
        "type": "Point", 
        "coordinates": [
          104.92158125, 
          -2.8201714574251402
        ]
      }, 
      "type": "Feature", 
      "properties": {
        "admin1_code": "", 
        "point_size": 8, 
        "name": "Palembang", 
        "geonameid": 1633070, 
        "font_file": "../fonts/Arial.ttf", 
        "zoom_start": 5, 
        "font_size": 18, 
        "country_code": "ID", 
        "capital": "no", 
        "asciiname": "Palembang", 
        "justified": "left", 
        "population": 1441500
      }
    }, 
    {
      "geometry": {
        "type": "Point", 
        "coordinates": [
          106.01695125000002, 
          21.114716093045455
        ]
      }, 
      "type": "Feature", 
      "properties": {
        "admin1_code": "", 
        "point_size": 8, 
        "name": "Hanoi", 
        "geonameid": 1581130, 
        "font_file": "../fonts/Arial.ttf", 
        "zoom_start": 5, 
        "font_size": 18, 
        "country_code": "VN", 
        "capital": "yes", 
        "asciiname": "Ha Noi", 
        "justified": "left", 
        "population": 1431270
      }
    }, 
    {
      "geometry": {
        "type": "Point", 
        "coordinates": [
          46.467681249999998, 
          38.156061842463359
        ]
      }, 
      "type": "Feature", 
      "properties": {
        "admin1_code": "", 
        "point_size": 8, 
        "name": "Tabriz", 
        "geonameid": 113646, 
        "font_file": "../fonts/Arial.ttf", 
        "zoom_start": 5, 
        "font_size": 18, 
        "country_code": "IR", 
        "capital": "no", 
        "asciiname": "Tabriz", 
        "justified": "left", 
        "population": 1424641
      }
    }, 
    {
      "geometry": {
        "type": "Point", 
        "coordinates": [
          83.110221249999995, 
          55.096468058137802
        ]
      }, 
      "type": "Feature", 
      "properties": {
        "admin1_code": "", 
        "point_size": 8, 
        "name": "Novosibirsk", 
        "geonameid": 1496747, 
        "font_file": "../fonts/Arial.ttf", 
        "zoom_start": 4, 
        "font_size": 18, 
        "country_code": "RU", 
        "capital": "no", 
        "asciiname": "Novosibirsk", 
        "justified": "left", 
        "population": 1419007
      }
    }, 
    {
      "geometry": {
        "type": "Point", 
        "coordinates": [
          130.59384124999994, 
          33.686872982509385
        ]
      }, 
      "type": "Feature", 
      "properties": {
        "admin1_code": "", 
        "point_size": 8, 
        "name": "Fukuoka", 
        "geonameid": 1863967, 
        "font_file": "../fonts/Arial.ttf", 
        "zoom_start": 5, 
        "font_size": 18, 
        "country_code": "JP", 
        "capital": "no", 
        "asciiname": "Fukuoka-shi", 
        "justified": "left", 
        "population": 1392289
      }
    }, 
    {
      "geometry": {
        "type": "Point", 
        "coordinates": [
          40.00189125, 
          21.234275776338233
        ]
      }, 
      "type": "Feature", 
      "properties": {
        "admin1_code": "", 
        "point_size": 8, 
        "name": "Mecca", 
        "geonameid": 104515, 
        "font_file": "../fonts/Arial.ttf", 
        "zoom_start": 5, 
        "font_size": 18, 
        "country_code": "SA", 
        "capital": "no", 
        "asciiname": "Mecca", 
        "justified": "left", 
        "population": 1323624
      }
    }, 
    {
      "geometry": {
        "type": "Point", 
        "coordinates": [
          119.59788124999996, 
          -5.0437018511994403
        ]
      }, 
      "type": "Feature", 
      "properties": {
        "admin1_code": "", 
        "point_size": 8, 
        "name": "Makassar", 
        "geonameid": 1622786, 
        "font_file": "../fonts/Arial.ttf", 
        "zoom_start": 5, 
        "font_size": 18, 
        "country_code": "ID", 
        "capital": "no", 
        "asciiname": "Makassar", 
        "justified": "left", 
        "population": 1321717
      }
    }, 
    {
      "geometry": {
        "type": "Point", 
        "coordinates": [
          109.99800125000002, 
          40.725528419050768
        ]
      }, 
      "type": "Feature", 
      "properties": {
        "admin1_code": "", 
        "point_size": 8, 
        "name": "Baotou", 
        "geonameid": 2038432, 
        "font_file": "../fonts/Arial.ttf", 
        "zoom_start": 5, 
        "font_size": 18, 
        "country_code": "CN", 
        "capital": "no", 
        "asciiname": "Baotou", 
        "justified": "left", 
        "population": 1301768
      }
    }, 
    {
      "geometry": {
        "type": "Point", 
        "coordinates": [
          39.789951250000001, 
          24.556575945083665
        ]
      }, 
      "type": "Feature", 
      "properties": {
        "admin1_code": "", 
        "point_size": 8, 
        "name": "Medina", 
        "geonameid": 109223, 
        "font_file": "../fonts/Arial.ttf", 
        "zoom_start": 5, 
        "font_size": 18, 
        "country_code": "SA", 
        "capital": "no", 
        "asciiname": "Medina", 
        "justified": "left", 
        "population": 1300000
      }
    }, 
    {
      "geometry": {
        "type": "Point", 
        "coordinates": [
          110.59608125, 
          -6.897229737649484
        ]
      }, 
      "type": "Feature", 
      "properties": {
        "admin1_code": "", 
        "point_size": 8, 
        "name": "Semarang", 
        "geonameid": 1627896, 
        "font_file": "../fonts/Arial.ttf", 
        "zoom_start": 5, 
        "font_size": 18, 
        "country_code": "ID", 
        "capital": "no", 
        "asciiname": "Semarang", 
        "justified": "left", 
        "population": 1288084
      }
    }, 
    {
      "geometry": {
        "type": "Point", 
        "coordinates": [
          60.788281250000004, 
          56.910319698403974
        ]
      }, 
      "type": "Feature", 
      "properties": {
        "admin1_code": "", 
        "point_size": 8, 
        "name": "Yekaterinburg", 
        "geonameid": 1486209, 
        "font_file": "../fonts/Arial.ttf", 
        "zoom_start": 5, 
        "font_size": 18, 
        "country_code": "RU", 
        "capital": "no", 
        "asciiname": "Yekaterinburg", 
        "justified": "left", 
        "population": 1287573
      }
    }, 
    {
      "geometry": {
        "type": "Point", 
        "coordinates": [
          44.177831249999983, 
          56.38223430504673
        ]
      }, 
      "type": "Feature", 
      "properties": {
        "admin1_code": "", 
        "point_size": 8, 
        "name": "Novgorod", 
        "geonameid": 520555, 
        "font_file": "../fonts/Arial.ttf", 
        "zoom_start": 5, 
        "font_size": 18, 
        "country_code": "RU", 
        "capital": "no", 
        "asciiname": "Nizhniy Novgorod", 
        "justified": "left", 
        "population": 1284164
      }
    }, 
    {
      "geometry": {
        "type": "Point", 
        "coordinates": [
          36.120811250000003, 
          32.037212395664092
        ]
      }, 
      "type": "Feature", 
      "properties": {
        "admin1_code": "", 
        "point_size": 8, 
        "name": "Amman", 
        "geonameid": 250441, 
        "font_file": "../fonts/Arial.ttf", 
        "zoom_start": 5, 
        "font_size": 18, 
        "country_code": "JO", 
        "capital": "yes", 
        "asciiname": "Amman", 
        "justified": "left", 
        "population": 1275857
      }
    }, 
    {
      "geometry": {
        "type": "Point", 
        "coordinates": [
          96.259371250000001, 
          22.064357474312576
        ]
      }, 
      "type": "Feature", 
      "properties": {
        "admin1_code": "", 
        "point_size": 8, 
        "name": "Mandalay", 
        "geonameid": 1311874, 
        "font_file": "../fonts/Arial.ttf", 
        "zoom_start": 5, 
        "font_size": 18, 
        "country_code": "MM", 
        "capital": "no", 
        "asciiname": "Mandalay", 
        "justified": "left", 
        "population": 1208099
      }
    }, 
    {
      "geometry": {
        "type": "Point", 
        "coordinates": [
          119.48189125000006, 
          26.148207450487494
        ]
      }, 
      "type": "Feature", 
      "properties": {
        "admin1_code": "", 
        "point_size": 8, 
        "name": "Fuzhou", 
        "geonameid": 1810821, 
        "font_file": "../fonts/Arial.ttf", 
        "zoom_start": 5, 
        "font_size": 18, 
        "country_code": "CN", 
        "capital": "no", 
        "asciiname": "Fuzhou", 
        "justified": "left", 
        "population": 1179720
      }
    }, 
    {
      "geometry": {
        "type": "Point", 
        "coordinates": [
          106.89245125000002, 
          26.669756476148599
        ]
      }, 
      "type": "Feature", 
      "properties": {
        "admin1_code": "", 
        "point_size": 8, 
        "name": "Guiyang", 
        "geonameid": 1809461, 
        "font_file": "../fonts/Arial.ttf", 
        "zoom_start": 5, 
        "font_size": 18, 
        "country_code": "CN", 
        "capital": "no", 
        "asciiname": "Guiyang", 
        "justified": "left", 
        "population": 1171633
      }
    }, 
    {
      "geometry": {
        "type": "Point", 
        "coordinates": [
          132.63515125000001, 
          34.225667612985198
        ]
      }, 
      "type": "Feature", 
      "properties": {
        "admin1_code": "", 
        "point_size": 8, 
        "name": "Hiroshima", 
        "geonameid": 1862415, 
        "font_file": "../fonts/Arial.ttf", 
        "zoom_start": 5, 
        "font_size": 18, 
        "country_code": "JP", 
        "capital": "no", 
        "asciiname": "Hiroshima-shi", 
        "justified": "left", 
        "population": 1143841
      }
    }, 
    {
      "geometry": {
        "type": "Point", 
        "coordinates": [
          55.455781250000008, 
          25.339629344669547
        ]
      }, 
      "type": "Feature", 
      "properties": {
        "admin1_code": "", 
        "point_size": 8, 
        "name": "Dubai", 
        "geonameid": 292223, 
        "font_file": "../fonts/Arial.ttf", 
        "zoom_start": 4, 
        "font_size": 18, 
        "country_code": "AE", 
        "capital": "no", 
        "asciiname": "Dubai", 
        "justified": "left", 
        "population": 1137347
      }
    }, 
    {
      "geometry": {
        "type": "Point", 
        "coordinates": [
          50.325781250000006, 
          53.257874297595684
        ]
      }, 
      "type": "Feature", 
      "properties": {
        "admin1_code": "", 
        "point_size": 8, 
        "name": "Samara", 
        "geonameid": 499099, 
        "font_file": "../fonts/Arial.ttf", 
        "zoom_start": 6, 
        "font_size": 18, 
        "country_code": "RU", 
        "capital": "no", 
        "asciiname": "Samara", 
        "justified": "left", 
        "population": 1134730
      }
    }, 
    {
      "geometry": {
        "type": "Point", 
        "coordinates": [
          73.575781250000006, 
          55.055414875382461
        ]
      }, 
      "type": "Feature", 
      "properties": {
        "admin1_code": "", 
        "point_size": 8, 
        "name": "Omsk", 
        "geonameid": 1496153, 
        "font_file": "../fonts/Arial.ttf", 
        "zoom_start": 5, 
        "font_size": 18, 
        "country_code": "RU", 
        "capital": "no", 
        "asciiname": "Omsk", 
        "justified": "left", 
        "population": 1129281
      }
    }, 
    {
      "geometry": {
        "type": "Point", 
        "coordinates": [
          50.067791250000028, 
          40.451279440940368
        ]
      }, 
      "type": "Feature", 
      "properties": {
        "admin1_code": "", 
        "point_size": 8, 
        "name": "Baku", 
        "geonameid": 587084, 
        "font_file": "../fonts/Arial.ttf", 
        "zoom_start": 4, 
        "font_size": 18, 
        "country_code": "AZ", 
        "capital": "yes", 
        "asciiname": "Baku", 
        "justified": "left", 
        "population": 1116513
      }
    }, 
    {
      "geometry": {
        "type": "Point", 
        "coordinates": [
          49.300581250000015, 
          55.842021293144924
        ]
      }, 
      "type": "Feature", 
      "properties": {
        "admin1_code": "", 
        "point_size": 8, 
        "name": "Kazan\u2019", 
        "geonameid": 551487, 
        "font_file": "../fonts/Arial.ttf", 
        "zoom_start": 6, 
        "font_size": 18, 
        "country_code": "RU", 
        "capital": "no", 
        "asciiname": "Kazan'", 
        "justified": "left", 
        "population": 1104738
      }
    }, 
    {
      "geometry": {
        "type": "Point", 
        "coordinates": [
          44.68939125, 
          40.254933917014327
        ]
      }, 
      "type": "Feature", 
      "properties": {
        "admin1_code": "", 
        "point_size": 8, 
        "name": "Yerevan", 
        "geonameid": 616052, 
        "font_file": "../fonts/Arial.ttf", 
        "zoom_start": 5, 
        "font_size": 18, 
        "country_code": "AM", 
        "capital": "yes", 
        "asciiname": "Yerevan", 
        "justified": "left", 
        "population": 1093485
      }
    }, 
    {
      "geometry": {
        "type": "Point", 
        "coordinates": [
          39.889671249999985, 
          47.301992448822119
        ]
      }, 
      "type": "Feature", 
      "properties": {
        "admin1_code": "", 
        "point_size": 8, 
        "name": "Rostov-na-Donu", 
        "geonameid": 501175, 
        "font_file": "../fonts/Arial.ttf", 
        "zoom_start": 6, 
        "font_size": 18, 
        "country_code": "RU", 
        "capital": "no", 
        "asciiname": "Rostov-na-Donu", 
        "justified": "left", 
        "population": 1074482
      }
    }, 
    {
      "geometry": {
        "type": "Point", 
        "coordinates": [
          61.605501249999946, 
          55.209641280008533
        ]
      }, 
      "type": "Feature", 
      "properties": {
        "admin1_code": "", 
        "point_size": 8, 
        "name": "Chelyabinsk", 
        "geonameid": 1508291, 
        "font_file": "../fonts/Arial.ttf", 
        "zoom_start": 5, 
        "font_size": 18, 
        "country_code": "RU", 
        "capital": "no", 
        "asciiname": "Chelyabinsk", 
        "justified": "left", 
        "population": 1062919
      }
    }, 
    {
      "geometry": {
        "type": "Point", 
        "coordinates": [
          45.00946125000003, 
          41.766260840767991
        ]
      }, 
      "type": "Feature", 
      "properties": {
        "admin1_code": "", 
        "point_size": 8, 
        "name": "Tbilisi", 
        "geonameid": 611717, 
        "font_file": "../fonts/Arial.ttf", 
        "zoom_start": 5, 
        "font_size": 18, 
        "country_code": "GE", 
        "capital": "yes", 
        "asciiname": "Tbilisi", 
        "justified": "left", 
        "population": 1049498
      }
    }, 
    {
      "geometry": {
        "type": "Point", 
        "coordinates": [
          56.213281249999994, 
          54.830725337954483
        ]
      }, 
      "type": "Feature", 
      "properties": {
        "admin1_code": "", 
        "point_size": 8, 
        "name": "Ufa", 
        "geonameid": 479561, 
        "font_file": "../fonts/Arial.ttf", 
        "zoom_start": 6, 
        "font_size": 18, 
        "country_code": "RU", 
        "capital": "no", 
        "asciiname": "Ufa", 
        "justified": "left", 
        "population": 1033338
      }
    }, 
    {
      "geometry": {
        "type": "Point", 
        "coordinates": [
          44.761611250000023, 
          48.868355477747528
        ]
      }, 
      "type": "Feature", 
      "properties": {
        "admin1_code": "", 
        "point_size": 8, 
        "name": "Volgograd", 
        "geonameid": 472757, 
        "font_file": "../fonts/Arial.ttf", 
        "zoom_start": 5, 
        "font_size": 18, 
        "country_code": "RU", 
        "capital": "no", 
        "asciiname": "Volgograd", 
        "justified": "left", 
        "population": 1011417
      }
    }, 
    {
      "geometry": {
        "type": "Point", 
        "coordinates": [
          56.425781249999993, 
          58.033750907663439
        ]
      }, 
      "type": "Feature", 
      "properties": {
        "admin1_code": "", 
        "point_size": 8, 
        "name": "Perm\u2019", 
        "geonameid": 511196, 
        "font_file": "../fonts/Arial.ttf", 
        "zoom_start": 6, 
        "font_size": 12, 
        "country_code": "RU", 
        "capital": "no", 
        "asciiname": "Perm'", 
        "justified": "left", 
        "population": 982419
      }
    }, 
    {
      "geometry": {
        "type": "Point", 
        "coordinates": [
          74.776061249999984, 
          42.919740870033422
        ]
      }, 
      "type": "Feature", 
      "properties": {
        "admin1_code": "", 
        "point_size": 8, 
        "name": "Bishkek", 
        "geonameid": 1528675, 
        "font_file": "../fonts/Arial.ttf", 
        "zoom_start": 5, 
        "font_size": 12, 
        "country_code": "KG", 
        "capital": "yes", 
        "asciiname": "Bishkek", 
        "justified": "left", 
        "population": 900000
      }
    }, 
    {
      "geometry": {
        "type": "Point", 
        "coordinates": [
          46.209111250000014, 
          51.606261764888231
        ]
      }, 
      "type": "Feature", 
      "properties": {
        "admin1_code": "", 
        "point_size": 8, 
        "name": "Saratov", 
        "geonameid": 498677, 
        "font_file": "../fonts/Arial.ttf", 
        "zoom_start": 5, 
        "font_size": 12, 
        "country_code": "RU", 
        "capital": "no", 
        "asciiname": "Saratov", 
        "justified": "left", 
        "population": 863725
      }
    }, 
    {
      "geometry": {
        "type": "Point", 
        "coordinates": [
          39.368051250000008, 
          51.709401784229485
        ]
      }, 
      "type": "Feature", 
      "properties": {
        "admin1_code": "", 
        "point_size": 8, 
        "name": "Voronezh", 
        "geonameid": 472045, 
        "font_file": "../fonts/Arial.ttf", 
        "zoom_start": 6, 
        "font_size": 12, 
        "country_code": "RU", 
        "capital": "no", 
        "asciiname": "Voronezh", 
        "justified": "left", 
        "population": 848752
      }
    }, 
    {
      "geometry": {
        "type": "Point", 
        "coordinates": [
          107.05902124999999, 
          47.950406068594539
        ]
      }, 
      "type": "Feature", 
      "properties": {
        "admin1_code": "", 
        "point_size": 8, 
        "name": "Ulaanbaatar", 
        "geonameid": 2028462, 
        "font_file": "../fonts/Arial.ttf", 
        "zoom_start": 5, 
        "font_size": 12, 
        "country_code": "MN", 
        "capital": "yes", 
        "asciiname": "Ulaanbaatar", 
        "justified": "left", 
        "population": 844818
      }
    }, 
    {
      "geometry": {
        "type": "Point", 
        "coordinates": [
          103.87429611388038, 
          1.6546169893944389
        ]
      }, 
      "type": "Feature", 
      "properties": {
        "admin1_code": "", 
        "point_size": 8, 
        "name": "Johor Baharu", 
        "geonameid": 1732752, 
        "font_file": "../fonts/Arial.ttf", 
        "zoom_start": 6, 
        "font_size": 12, 
        "country_code": "MY", 
        "capital": "no", 
        "asciiname": "Johor Bahru", 
        "justified": "left", 
        "population": 802489
      }
    }, 
    {
      "geometry": {
        "type": "Point", 
        "coordinates": [
          105.44245125000002, 
          -5.386564011556275
        ]
      }, 
      "type": "Feature", 
      "properties": {
        "admin1_code": "", 
        "point_size": 8, 
        "name": "Bandar Lampung", 
        "geonameid": 1624917, 
        "font_file": "../fonts/Arial.ttf", 
        "zoom_start": 5, 
        "font_size": 12, 
        "country_code": "ID", 
        "capital": "no", 
        "asciiname": "Tanjungkarang-Telukbetung", 
        "justified": "left", 
        "population": 800348
      }
    }, 
    {
      "geometry": {
        "type": "Point", 
        "coordinates": [
          58.76911125000003, 
          23.671702327871454
        ]
      }, 
      "type": "Feature", 
      "properties": {
        "admin1_code": "", 
        "point_size": 8, 
        "name": "Muscat", 
        "geonameid": 287286, 
        "font_file": "../fonts/Arial.ttf", 
        "zoom_start": 5, 
        "font_size": 12, 
        "country_code": "OM", 
        "capital": "yes", 
        "asciiname": "Muscat", 
        "justified": "left", 
        "population": 797000
      }
    }, 
    {
      "geometry": {
        "type": "Point", 
        "coordinates": [
          67.188281250000003, 
          30.24228394004718
        ]
      }, 
      "type": "Feature", 
      "properties": {
        "admin1_code": "", 
        "point_size": 8, 
        "name": "Quetta", 
        "geonameid": 1167528, 
        "font_file": "../fonts/Arial.ttf", 
        "zoom_start": 5, 
        "font_size": 12, 
        "country_code": "PK", 
        "capital": "no", 
        "asciiname": "Quetta", 
        "justified": "left", 
        "population": 733675
      }
    }, 
    {
      "geometry": {
        "type": "Point", 
        "coordinates": [
          58.559111250000043, 
          38.000229629854218
        ]
      }, 
      "type": "Feature", 
      "properties": {
        "admin1_code": "", 
        "point_size": 8, 
        "name": "Ashgabat", 
        "geonameid": 162183, 
        "font_file": "../fonts/Arial.ttf", 
        "zoom_start": 5, 
        "font_size": 12, 
        "country_code": "TM", 
        "capital": "yes", 
        "asciiname": "Ashgabat", 
        "justified": "left", 
        "population": 727700
      }
    }, 
    {
      "geometry": {
        "type": "Point", 
        "coordinates": [
          35.349596113880452, 
          31.469244367279501
        ]
      }, 
      "type": "Feature", 
      "properties": {
        "admin1_code": "", 
        "point_size": 8, 
        "name": "Jerusalem", 
        "geonameid": 281184, 
        "font_file": "../fonts/Arial.ttf", 
        "zoom_start": 6, 
        "font_size": 12, 
        "country_code": "IL", 
        "capital": "no", 
        "asciiname": "Jerusalem", 
        "justified": "left", 
        "population": 714000
      }
    }, 
    {
      "geometry": {
        "type": "Point", 
        "coordinates": [
          80.023561250000014, 
          6.995190660754826
        ]
      }, 
      "type": "Feature", 
      "properties": {
        "admin1_code": "", 
        "point_size": 8, 
        "name": "Colombo", 
        "geonameid": 1248991, 
        "font_file": "../fonts/Arial.ttf", 
        "zoom_start": 5, 
        "font_size": 12, 
        "country_code": "LK", 
        "capital": "yes", 
        "asciiname": "Colombo", 
        "justified": "left", 
        "population": 648034
      }
    }, 
    {
      "geometry": {
        "type": "Point", 
        "coordinates": [
          53.409111250000038, 
          56.884828351068869
        ]
      }, 
      "type": "Feature", 
      "properties": {
        "admin1_code": "", 
        "point_size": 8, 
        "name": "Izhevsk", 
        "geonameid": 554840, 
        "font_file": "../fonts/Arial.ttf", 
        "zoom_start": 6, 
        "font_size": 12, 
        "country_code": "RU", 
        "capital": "no", 
        "asciiname": "Izhevsk", 
        "justified": "left", 
        "population": 631038
      }
    }, 
    {
      "geometry": {
        "type": "Point", 
        "coordinates": [
          76.409111249999967, 
          10.029423016356048
        ]
      }, 
      "type": "Feature", 
      "properties": {
        "admin1_code": "", 
        "point_size": 8, 
        "name": "Cochin", 
        "geonameid": 1273874, 
        "font_file": "../fonts/Arial.ttf", 
        "zoom_start": 5, 
        "font_size": 12, 
        "country_code": "IN", 
        "capital": "no", 
        "asciiname": "Cochin", 
        "justified": "left", 
        "population": 604696
      }
    }, 
    {
      "geometry": {
        "type": "Point", 
        "coordinates": [
          54.542451249999992, 
          24.524655368678271
        ]
      }, 
      "type": "Feature", 
      "properties": {
        "admin1_code": "", 
        "point_size": 8, 
        "name": "Abu Dhabi", 
        "geonameid": 292968, 
        "font_file": "../fonts/Arial.ttf", 
        "zoom_start": 5, 
        "font_size": 12, 
        "country_code": "AE", 
        "capital": "yes", 
        "asciiname": "Abu Dhabi", 
        "justified": "left", 
        "population": 603492
      }
    }, 
    {
      "geometry": {
        "type": "Point", 
        "coordinates": [
          73.219071249999999, 
          33.774463078041144
        ]
      }, 
      "type": "Feature", 
      "properties": {
        "admin1_code": "", 
        "point_size": 8, 
        "name": "Islamabad", 
        "geonameid": 1176615, 
        "font_file": "../fonts/Arial.ttf", 
        "zoom_start": 4, 
        "font_size": 12, 
        "country_code": "PK", 
        "capital": "yes", 
        "asciiname": "Islamabad", 
        "justified": "left", 
        "population": 601600
      }
    }, 
    {
      "geometry": {
        "type": "Point", 
        "coordinates": [
          132.04931124999996, 
          43.152124504404355
        ]
      }, 
      "type": "Feature", 
      "properties": {
        "admin1_code": "", 
        "point_size": 8, 
        "name": "Vladivostok", 
        "geonameid": 2013348, 
        "font_file": "../fonts/Arial.ttf", 
        "zoom_start": 5, 
        "font_size": 12, 
        "country_code": "RU", 
        "capital": "no", 
        "asciiname": "Vladivostok", 
        "justified": "left", 
        "population": 587022
      }
    }, 
    {
      "geometry": {
        "type": "Point", 
        "coordinates": [
          68.954831249999984, 
          38.58557631214132
        ]
      }, 
      "type": "Feature", 
      "properties": {
        "admin1_code": "", 
        "point_size": 8, 
        "name": "Dushanbe", 
        "geonameid": 1221874, 
        "font_file": "../fonts/Arial.ttf", 
        "zoom_start": 5, 
        "font_size": 12, 
        "country_code": "TJ", 
        "capital": "yes", 
        "asciiname": "Dushanbe", 
        "justified": "left", 
        "population": 543107
      }
    }, 
    {
      "geometry": {
        "type": "Point", 
        "coordinates": [
          113.37032874999998, 
          22.259544484813294
        ]
      }, 
      "type": "Feature", 
      "properties": {
        "admin1_code": "", 
        "point_size": 8, 
        "name": "Macau", 
        "geonameid": 1821274, 
        "font_file": "../fonts/Arial.ttf", 
        "zoom_start": 5, 
        "font_size": 12, 
        "country_code": "MO", 
        "capital": "yes", 
        "asciiname": "Macau", 
        "justified": "right", 
        "population": 520400
      }
    }, 
    {
      "geometry": {
        "type": "Point", 
        "coordinates": [
          48.224951249999982, 
          46.393406048553501
        ]
      }, 
      "type": "Feature", 
      "properties": {
        "admin1_code": "", 
        "point_size": 8, 
        "name": "Astrakhan", 
        "geonameid": 580497, 
        "font_file": "../fonts/Arial.ttf", 
        "zoom_start": 6, 
        "font_size": 12, 
        "country_code": "RU", 
        "capital": "no", 
        "asciiname": "Astrakhan'", 
        "justified": "left", 
        "population": 502533
      }
    }, 
    {
      "geometry": {
        "type": "Point", 
        "coordinates": [
          20.675781249999996, 
          54.746795710964555
        ]
      }, 
      "type": "Feature", 
      "properties": {
        "admin1_code": "", 
        "point_size": 8, 
        "name": "Kaliningrad", 
        "geonameid": 554234, 
        "font_file": "../fonts/Arial.ttf", 
        "zoom_start": 6, 
        "font_size": 12, 
        "country_code": "RU", 
        "capital": "no", 
        "asciiname": "Kaliningrad", 
        "justified": "left", 
        "population": 434954
      }
    }, 
    {
      "geometry": {
        "type": "Point", 
        "coordinates": [
          41.161611249999993, 
          57.028864036408777
        ]
      }, 
      "type": "Feature", 
      "properties": {
        "admin1_code": "", 
        "point_size": 8, 
        "name": "Ivanovo", 
        "geonameid": 555312, 
        "font_file": "../fonts/Arial.ttf", 
        "zoom_start": 6, 
        "font_size": 12, 
        "country_code": "RU", 
        "capital": "no", 
        "asciiname": "Ivanovo", 
        "justified": "left", 
        "population": 420839
      }
    }, 
    {
      "geometry": {
        "type": "Point", 
        "coordinates": [
          130.04939125000001, 
          32.798298649105064
        ]
      }, 
      "type": "Feature", 
      "properties": {
        "admin1_code": "", 
        "point_size": 8, 
        "name": "Nagasaki", 
        "geonameid": 1856177, 
        "font_file": "../fonts/Arial.ttf", 
        "zoom_start": 6, 
        "font_size": 12, 
        "country_code": "JP", 
        "capital": "no", 
        "asciiname": "Nagasaki-shi", 
        "justified": "left", 
        "population": 410204
      }
    }, 
    {
      "geometry": {
        "type": "Point", 
        "coordinates": [
          115.39245124999997, 
          -8.5869988313043759
        ]
      }, 
      "type": "Feature", 
      "properties": {
        "admin1_code": "", 
        "point_size": 8, 
        "name": "Denpasar", 
        "geonameid": 1645528, 
        "font_file": "../fonts/Arial.ttf", 
        "zoom_start": 5, 
        "font_size": 12, 
        "country_code": "ID", 
        "capital": "no", 
        "asciiname": "Denpasar", 
        "justified": "left", 
        "population": 405923
      }
    }, 
    {
      "geometry": {
        "type": "Point", 
        "coordinates": [
          40.724391249999989, 
          64.574591314787426
        ]
      }, 
      "type": "Feature", 
      "properties": {
        "admin1_code": "", 
        "point_size": 8, 
        "name": "Arkhangel\u2019sk", 
        "geonameid": 581049, 
        "font_file": "../fonts/Arial.ttf", 
        "zoom_start": 6, 
        "font_size": 12, 
        "country_code": "RU", 
        "capital": "no", 
        "asciiname": "Arkhangel'sk", 
        "justified": "left", 
        "population": 356051
      }
    }, 
    {
      "geometry": {
        "type": "Point", 
        "coordinates": [
          51.698231250000028, 
          25.336924911215917
        ]
      }, 
      "type": "Feature", 
      "properties": {
        "admin1_code": "", 
        "point_size": 8, 
        "name": "Doha", 
        "geonameid": 290030, 
        "font_file": "../fonts/Arial.ttf", 
        "zoom_start": 5, 
        "font_size": 12, 
        "country_code": "QA", 
        "capital": "yes", 
        "asciiname": "Doha", 
        "justified": "left", 
        "population": 344939
      }
    }, 
    {
      "geometry": {
        "type": "Point", 
        "coordinates": [
          32.215881249999974, 
          54.818530519149284
        ]
      }, 
      "type": "Feature", 
      "properties": {
        "admin1_code": "", 
        "point_size": 8, 
        "name": "Smolensk", 
        "geonameid": 491687, 
        "font_file": "../fonts/Arial.ttf", 
        "zoom_start": 6, 
        "font_size": 12, 
        "country_code": "RU", 
        "capital": "no", 
        "asciiname": "Smolensk", 
        "justified": "left", 
        "population": 320991
      }
    }, 
    {
      "geometry": {
        "type": "Point", 
        "coordinates": [
          33.25772125000001, 
          68.994523004892969
        ]
      }, 
      "type": "Feature", 
      "properties": {
        "admin1_code": "", 
        "point_size": 8, 
        "name": "Murmansk", 
        "geonameid": 524305, 
        "font_file": "../fonts/Arial.ttf", 
        "zoom_start": 6, 
        "font_size": 12, 
        "country_code": "RU", 
        "capital": "no", 
        "asciiname": "Murmansk", 
        "justified": "left", 
        "population": 319263
      }
    }, 
    {
      "geometry": {
        "type": "Point", 
        "coordinates": [
          77.400231250000004, 
          28.691671733948962
        ]
      }, 
      "type": "Feature", 
      "properties": {
        "admin1_code": "", 
        "point_size": 8, 
        "name": "New Delhi", 
        "geonameid": 1261481, 
        "font_file": "../fonts/Arial.ttf", 
        "zoom_start": 4, 
        "font_size": 12, 
        "country_code": "IN", 
        "capital": "yes", 
        "asciiname": "New Delhi", 
        "justified": "left", 
        "population": 317797
      }
    }, 
    {
      "geometry": {
        "type": "Point", 
        "coordinates": [
          100.51121124999999, 
          5.474663392415037
        ]
      }, 
      "type": "Feature", 
      "properties": {
        "admin1_code": "", 
        "point_size": 8, 
        "name": "George Town", 
        "geonameid": 1735106, 
        "font_file": "../fonts/Arial.ttf", 
        "zoom_start": 6, 
        "font_size": 12, 
        "country_code": "MY", 
        "capital": "no", 
        "asciiname": "George Town", 
        "justified": "left", 
        "population": 300000
      }
    }, 
    {
      "geometry": {
        "type": "Point", 
        "coordinates": [
          147.35550124999997, 
          -9.3802770595632303
        ]
      }, 
      "type": "Feature", 
      "properties": {
        "admin1_code": "", 
        "point_size": 8, 
        "name": "Port Moresby", 
        "geonameid": 2088122, 
        "font_file": "../fonts/Arial.ttf", 
        "zoom_start": 4, 
        "font_size": 12, 
        "country_code": "PG", 
        "capital": "yes", 
        "asciiname": "Port Moresby", 
        "justified": "left", 
        "population": 283733
      }
    }, 
    {
      "geometry": {
        "type": "Point", 
        "coordinates": [
          35.164951249999994, 
          32.869095976180247
        ]
      }, 
      "type": "Feature", 
      "properties": {
        "admin1_code": "", 
        "point_size": 8, 
        "name": "Haifa", 
        "geonameid": 294801, 
        "font_file": "../fonts/Arial.ttf", 
        "zoom_start": 6, 
        "font_size": 12, 
        "country_code": "IL", 
        "capital": "no", 
        "asciiname": "Haifa", 
        "justified": "left", 
        "population": 267300
      }
    }, 
    {
      "geometry": {
        "type": "Point", 
        "coordinates": [
          34.890966113880438, 
          32.225862345168075
        ]
      }, 
      "type": "Feature", 
      "properties": {
        "admin1_code": "", 
        "point_size": 8, 
        "name": "Tel Aviv", 
        "geonameid": 293397, 
        "font_file": "../fonts/Arial.ttf", 
        "zoom_start": 4, 
        "font_size": 12, 
        "country_code": "IL", 
        "capital": "no", 
        "asciiname": "Tel Aviv", 
        "justified": "left", 
        "population": 250000
      }
    }, 
    {
      "geometry": {
        "type": "Point", 
        "coordinates": [
          102.77578124999998, 
          18.027273027220666
        ]
      }, 
      "type": "Feature", 
      "properties": {
        "admin1_code": "", 
        "point_size": 8, 
        "name": "Vientiane", 
        "geonameid": 1651944, 
        "font_file": "../fonts/Arial.ttf", 
        "zoom_start": 5, 
        "font_size": 12, 
        "country_code": "LA", 
        "capital": "yes", 
        "asciiname": "Vientiane", 
        "justified": "left", 
        "population": 196731
      }
    }, 
    {
      "geometry": {
        "type": "Point", 
        "coordinates": [
          50.758981250000012, 
          26.272512340570874
        ]
      }, 
      "type": "Feature", 
      "properties": {
        "admin1_code": "", 
        "point_size": 8, 
        "name": "Manama", 
        "geonameid": 290340, 
        "font_file": "../fonts/Arial.ttf", 
        "zoom_start": 5, 
        "font_size": 12, 
        "country_code": "BH", 
        "capital": "yes", 
        "asciiname": "Manama", 
        "justified": "left", 
        "population": 147074
      }
    }, 
    {
      "geometry": {
        "type": "Point", 
        "coordinates": [
          115.41745125, 
          5.3401174116344636
        ]
      }, 
      "type": "Feature", 
      "properties": {
        "admin1_code": "", 
        "point_size": 8, 
        "name": "Labuan", 
        "geonameid": 1733782, 
        "font_file": "../fonts/Arial.ttf", 
        "zoom_start": 6, 
        "font_size": 12, 
        "country_code": "MY", 
        "capital": "no", 
        "asciiname": "Victoria", 
        "justified": "left", 
        "population": 73653
      }
    }, 
    {
      "geometry": {
        "type": "Point", 
        "coordinates": [
          48.15411125, 
          29.425235729976702
        ]
      }, 
      "type": "Feature", 
      "properties": {
        "admin1_code": "", 
        "point_size": 8, 
        "name": "Kuwait", 
        "geonameid": 285787, 
        "font_file": "../fonts/Arial.ttf", 
        "zoom_start": 5, 
        "font_size": 12, 
        "country_code": "KW", 
        "capital": "yes", 
        "asciiname": "Kuwait", 
        "justified": "left", 
        "population": 60064
      }
    }, 
    {
      "geometry": {
        "type": "Point", 
        "coordinates": [
          34.473281249999978, 
          54.112089996709543
        ]
      }, 
      "type": "Feature", 
      "properties": {
        "admin1_code": "", 
        "point_size": 8, 
        "name": "Kirov", 
        "geonameid": 548410, 
        "font_file": "../fonts/Arial.ttf", 
        "zoom_start": 6, 
        "font_size": 12, 
        "country_code": "RU", 
        "capital": "no", 
        "asciiname": "Kirov", 
        "justified": "left", 
        "population": 39319
      }
    }
  ]
}